<stg><name>applyMixer_hls<3>_Pipeline_VITIS_LOOP_166_7</name>


<trans_list>

<trans id="52" from="1" to="2">
<condition id="-1">
<or_exp><and_exp></and_exp></or_exp>
</condition>
</trans>
</trans_list>



<state_list>

<state id="1" st_id="2">

<operation id="5" st_id="1" stage="1" lat="1">
<core>NULL</core>
<MemPortIdVec></MemPortIdVec>
<condition id="-1">
<or_exp><and_exp></and_exp></or_exp>
</condition>

<Node id="8" bw="10" op_0_bw="32">
<![CDATA[
newFuncRoot:0 %k = alloca i32 1

]]></Node>
<StgValue><ssdm name="k"/></StgValue>
</operation>

<operation id="6" st_id="1" stage="1" lat="1">
<core>NULL</core>
<MemPortIdVec></MemPortIdVec>
<condition id="-1">
<or_exp><and_exp></and_exp></or_exp>
</condition>

<Node id="9" bw="0" op_0_bw="0" op_1_bw="32" op_2_bw="64" op_3_bw="64" op_4_bw="64">
<![CDATA[
newFuncRoot:1 %specmemcore_ln0 = specmemcore void @_ssdm_op_SpecMemCore, i32 %bufB_im, i64 666, i64 22, i64 18446744073709551615

]]></Node>
<StgValue><ssdm name="specmemcore_ln0"/></StgValue>
</operation>

<operation id="7" st_id="1" stage="1" lat="1">
<core>NULL</core>
<MemPortIdVec></MemPortIdVec>
<condition id="-1">
<or_exp><and_exp></and_exp></or_exp>
</condition>

<Node id="10" bw="0" op_0_bw="0" op_1_bw="32" op_2_bw="64" op_3_bw="64" op_4_bw="64">
<![CDATA[
newFuncRoot:2 %specmemcore_ln0 = specmemcore void @_ssdm_op_SpecMemCore, i32 %bufB_re, i64 666, i64 22, i64 18446744073709551615

]]></Node>
<StgValue><ssdm name="specmemcore_ln0"/></StgValue>
</operation>

<operation id="8" st_id="1" stage="1" lat="1">
<core>NULL</core>
<MemPortIdVec></MemPortIdVec>
<condition id="-1">
<or_exp><and_exp></and_exp></or_exp>
</condition>

<Node id="11" bw="0" op_0_bw="0" op_1_bw="32" op_2_bw="64" op_3_bw="64" op_4_bw="64">
<![CDATA[
newFuncRoot:3 %specmemcore_ln0 = specmemcore void @_ssdm_op_SpecMemCore, i32 %bufA_im, i64 666, i64 22, i64 18446744073709551615

]]></Node>
<StgValue><ssdm name="specmemcore_ln0"/></StgValue>
</operation>

<operation id="9" st_id="1" stage="1" lat="1">
<core>NULL</core>
<MemPortIdVec></MemPortIdVec>
<condition id="-1">
<or_exp><and_exp></and_exp></or_exp>
</condition>

<Node id="12" bw="0" op_0_bw="0" op_1_bw="32" op_2_bw="64" op_3_bw="64" op_4_bw="64">
<![CDATA[
newFuncRoot:4 %specmemcore_ln0 = specmemcore void @_ssdm_op_SpecMemCore, i32 %bufA_re, i64 666, i64 22, i64 18446744073709551615

]]></Node>
<StgValue><ssdm name="specmemcore_ln0"/></StgValue>
</operation>

<operation id="10" st_id="1" stage="1" lat="1">
<core>NULL</core>
<MemPortIdVec></MemPortIdVec>
<condition id="-1">
<or_exp><and_exp></and_exp></or_exp>
</condition>

<Node id="13" bw="0" op_0_bw="0" op_1_bw="32" op_2_bw="64" op_3_bw="64" op_4_bw="64">
<![CDATA[
newFuncRoot:5 %specmemcore_ln0 = specmemcore void @_ssdm_op_SpecMemCore, i32 %state_im, i64 666, i64 22, i64 18446744073709551615

]]></Node>
<StgValue><ssdm name="specmemcore_ln0"/></StgValue>
</operation>

<operation id="11" st_id="1" stage="1" lat="1">
<core>NULL</core>
<MemPortIdVec></MemPortIdVec>
<condition id="-1">
<or_exp><and_exp></and_exp></or_exp>
</condition>

<Node id="14" bw="0" op_0_bw="0" op_1_bw="32" op_2_bw="64" op_3_bw="64" op_4_bw="64">
<![CDATA[
newFuncRoot:6 %specmemcore_ln0 = specmemcore void @_ssdm_op_SpecMemCore, i32 %state_re, i64 666, i64 22, i64 18446744073709551615

]]></Node>
<StgValue><ssdm name="specmemcore_ln0"/></StgValue>
</operation>

<operation id="12" st_id="1" stage="1" lat="1">
<core>NULL</core>
<MemPortIdVec></MemPortIdVec>
<condition id="-1">
<or_exp><and_exp></and_exp></or_exp>
</condition>

<Node id="15" bw="1" op_0_bw="1" op_1_bw="1">
<![CDATA[
newFuncRoot:7 %state_cur_030126_read = read i1 @_ssdm_op_Read.ap_auto.i1, i1 %state_cur_030126

]]></Node>
<StgValue><ssdm name="state_cur_030126_read"/></StgValue>
</operation>

<operation id="13" st_id="1" stage="1" lat="1">
<core>NULL</core>
<MemPortIdVec></MemPortIdVec>
<condition id="-1">
<or_exp><and_exp></and_exp></or_exp>
</condition>

<Node id="16" bw="0" op_0_bw="10" op_1_bw="10">
<![CDATA[
newFuncRoot:8 %store_ln166 = store i10 0, i10 %k

]]></Node>
<StgValue><ssdm name="store_ln166"/></StgValue>
</operation>

<operation id="14" st_id="1" stage="1" lat="1">
<core>NULL</core>
<MemPortIdVec></MemPortIdVec>
<condition id="-1">
<or_exp><and_exp></and_exp></or_exp>
</condition>

<Node id="17" bw="0" op_0_bw="0">
<![CDATA[
newFuncRoot:9 %br_ln0 = br void %for.inc100

]]></Node>
<StgValue><ssdm name="br_ln0"/></StgValue>
</operation>

<operation id="15" st_id="1" stage="1" lat="1">
<core>NULL</core>
<MemPortIdVec></MemPortIdVec>
<condition id="-1">
<or_exp><and_exp></and_exp></or_exp>
</condition>

<Node id="19" bw="10" op_0_bw="10" op_1_bw="0">
<![CDATA[
for.inc100:0 %k_1 = load i10 %k

]]></Node>
<StgValue><ssdm name="k_1"/></StgValue>
</operation>

<operation id="16" st_id="1" stage="1" lat="1">
<core>Cmp</core>
<MemPortIdVec></MemPortIdVec>
<condition id="-1">
<or_exp><and_exp></and_exp></or_exp>
</condition>

<Node id="20" bw="1" op_0_bw="10" op_1_bw="10">
<![CDATA[
for.inc100:1 %icmp_ln166 = icmp_eq  i10 %k_1, i10 512

]]></Node>
<StgValue><ssdm name="icmp_ln166"/></StgValue>
</operation>

<operation id="17" st_id="1" stage="1" lat="1">
<core>Adder</core>
<MemPortIdVec></MemPortIdVec>
<condition id="-1">
<or_exp><and_exp></and_exp></or_exp>
</condition>

<Node id="21" bw="10" op_0_bw="10" op_1_bw="10">
<![CDATA[
for.inc100:2 %add_ln166 = add i10 %k_1, i10 1

]]></Node>
<StgValue><ssdm name="add_ln166"/></StgValue>
</operation>

<operation id="18" st_id="1" stage="1" lat="1">
<core>NULL</core>
<MemPortIdVec></MemPortIdVec>
<condition id="-1">
<or_exp><and_exp></and_exp></or_exp>
</condition>

<Node id="22" bw="0" op_0_bw="1" op_1_bw="0" op_2_bw="0">
<![CDATA[
for.inc100:3 %br_ln166 = br i1 %icmp_ln166, void %for.inc100.split_ifconv, void %for.end102.exitStub

]]></Node>
<StgValue><ssdm name="br_ln166"/></StgValue>
</operation>

<operation id="19" st_id="1" stage="1" lat="1">
<core>NULL</core>
<MemPortIdVec></MemPortIdVec>
<condition id="-1">
<or_exp><and_exp><literal name="icmp_ln166" val="0"/>
</and_exp></or_exp>
</condition>

<Node id="24" bw="64" op_0_bw="10">
<![CDATA[
for.inc100.split_ifconv:0 %zext_ln166 = zext i10 %k_1

]]></Node>
<StgValue><ssdm name="zext_ln166"/></StgValue>
</operation>

<operation id="20" st_id="1" stage="1" lat="1">
<core>NULL</core>
<MemPortIdVec></MemPortIdVec>
<condition id="-1">
<or_exp><and_exp><literal name="icmp_ln166" val="0"/>
<literal name="state_cur_030126_read" val="1"/>
</and_exp></or_exp>
</condition>

<Node id="30" bw="9" op_0_bw="32" op_1_bw="64" op_2_bw="64">
<![CDATA[
for.inc100.split_ifconv:6 %bufB_re_addr = getelementptr i32 %bufB_re, i64 0, i64 %zext_ln166

]]></Node>
<StgValue><ssdm name="bufB_re_addr"/></StgValue>
</operation>

<operation id="21" st_id="1" stage="2" lat="2">
<core>RAM_2P_BRAM</core>
<MemPortIdVec></MemPortIdVec>
<condition id="-1">
<or_exp><and_exp><literal name="icmp_ln166" val="0"/>
<literal name="state_cur_030126_read" val="1"/>
</and_exp></or_exp>
</condition>

<Node id="31" bw="32" op_0_bw="9">
<![CDATA[
for.inc100.split_ifconv:7 %bufB_re_load = load i9 %bufB_re_addr

]]></Node>
<StgValue><ssdm name="bufB_re_load"/></StgValue>
</operation>

<operation id="22" st_id="1" stage="1" lat="1">
<core>NULL</core>
<MemPortIdVec></MemPortIdVec>
<condition id="-1">
<or_exp><and_exp><literal name="icmp_ln166" val="0"/>
<literal name="state_cur_030126_read" val="1"/>
</and_exp></or_exp>
</condition>

<Node id="32" bw="9" op_0_bw="32" op_1_bw="64" op_2_bw="64">
<![CDATA[
for.inc100.split_ifconv:8 %bufB_im_addr = getelementptr i32 %bufB_im, i64 0, i64 %zext_ln166

]]></Node>
<StgValue><ssdm name="bufB_im_addr"/></StgValue>
</operation>

<operation id="23" st_id="1" stage="2" lat="2">
<core>RAM_2P_BRAM</core>
<MemPortIdVec></MemPortIdVec>
<condition id="-1">
<or_exp><and_exp><literal name="icmp_ln166" val="0"/>
<literal name="state_cur_030126_read" val="1"/>
</and_exp></or_exp>
</condition>

<Node id="33" bw="32" op_0_bw="9">
<![CDATA[
for.inc100.split_ifconv:9 %bufB_im_load = load i9 %bufB_im_addr

]]></Node>
<StgValue><ssdm name="bufB_im_load"/></StgValue>
</operation>

<operation id="24" st_id="1" stage="1" lat="1">
<core>NULL</core>
<MemPortIdVec></MemPortIdVec>
<condition id="-1">
<or_exp><and_exp><literal name="icmp_ln166" val="0"/>
<literal name="state_cur_030126_read" val="0"/>
</and_exp></or_exp>
</condition>

<Node id="34" bw="9" op_0_bw="32" op_1_bw="64" op_2_bw="64">
<![CDATA[
for.inc100.split_ifconv:10 %bufA_re_addr = getelementptr i32 %bufA_re, i64 0, i64 %zext_ln166

]]></Node>
<StgValue><ssdm name="bufA_re_addr"/></StgValue>
</operation>

<operation id="25" st_id="1" stage="2" lat="2">
<core>RAM_2P_BRAM</core>
<MemPortIdVec></MemPortIdVec>
<condition id="-1">
<or_exp><and_exp><literal name="icmp_ln166" val="0"/>
<literal name="state_cur_030126_read" val="0"/>
</and_exp></or_exp>
</condition>

<Node id="35" bw="32" op_0_bw="9">
<![CDATA[
for.inc100.split_ifconv:11 %bufA_re_load = load i9 %bufA_re_addr

]]></Node>
<StgValue><ssdm name="bufA_re_load"/></StgValue>
</operation>

<operation id="26" st_id="1" stage="1" lat="1">
<core>NULL</core>
<MemPortIdVec></MemPortIdVec>
<condition id="-1">
<or_exp><and_exp><literal name="icmp_ln166" val="0"/>
<literal name="state_cur_030126_read" val="0"/>
</and_exp></or_exp>
</condition>

<Node id="36" bw="9" op_0_bw="32" op_1_bw="64" op_2_bw="64">
<![CDATA[
for.inc100.split_ifconv:12 %bufA_im_addr = getelementptr i32 %bufA_im, i64 0, i64 %zext_ln166

]]></Node>
<StgValue><ssdm name="bufA_im_addr"/></StgValue>
</operation>

<operation id="27" st_id="1" stage="2" lat="2">
<core>RAM_2P_BRAM</core>
<MemPortIdVec></MemPortIdVec>
<condition id="-1">
<or_exp><and_exp><literal name="icmp_ln166" val="0"/>
<literal name="state_cur_030126_read" val="0"/>
</and_exp></or_exp>
</condition>

<Node id="37" bw="32" op_0_bw="9">
<![CDATA[
for.inc100.split_ifconv:13 %bufA_im_load = load i9 %bufA_im_addr

]]></Node>
<StgValue><ssdm name="bufA_im_load"/></StgValue>
</operation>

<operation id="28" st_id="1" stage="1" lat="1">
<core>NULL</core>
<MemPortIdVec></MemPortIdVec>
<condition id="-1">
<or_exp><and_exp><literal name="icmp_ln166" val="0"/>
</and_exp></or_exp>
</condition>

<Node id="42" bw="0" op_0_bw="10" op_1_bw="10" op_2_bw="0" op_3_bw="0">
<![CDATA[
for.inc100.split_ifconv:18 %store_ln166 = store i10 %add_ln166, i10 %k

]]></Node>
<StgValue><ssdm name="store_ln166"/></StgValue>
</operation>

<operation id="43" st_id="1" stage="1" lat="1">
<core>NULL</core>
<MemPortIdVec></MemPortIdVec>
<condition id="-1">
<or_exp><and_exp><literal name="icmp_ln166" val="1"/>
</and_exp></or_exp>
</condition>

<Node id="45" bw="0">
<![CDATA[
for.end102.exitStub:0 %ret_ln0 = ret

]]></Node>
<StgValue><ssdm name="ret_ln0"/></StgValue>
</operation>
</state>

<state id="2" st_id="3">

<operation id="29" st_id="2" stage="1" lat="1">
<core>NULL</core>
<MemPortIdVec></MemPortIdVec>
<condition id="-1">
<or_exp><and_exp></and_exp></or_exp>
</condition>

<Node id="25" bw="0" op_0_bw="0" op_1_bw="32" op_2_bw="32" op_3_bw="32" op_4_bw="32" op_5_bw="0">
<![CDATA[
for.inc100.split_ifconv:1 %specpipeline_ln166 = specpipeline void @_ssdm_op_SpecPipeline, i32 4294967295, i32 0, i32 0, i32 0, void @empty_0

]]></Node>
<StgValue><ssdm name="specpipeline_ln166"/></StgValue>
</operation>

<operation id="30" st_id="2" stage="1" lat="1">
<core>NULL</core>
<MemPortIdVec></MemPortIdVec>
<condition id="-1">
<or_exp><and_exp></and_exp></or_exp>
</condition>

<Node id="26" bw="0" op_0_bw="0" op_1_bw="64" op_2_bw="64" op_3_bw="64">
<![CDATA[
for.inc100.split_ifconv:2 %speclooptripcount_ln166 = speclooptripcount void @_ssdm_op_SpecLoopTripCount, i64 512, i64 512, i64 512

]]></Node>
<StgValue><ssdm name="speclooptripcount_ln166"/></StgValue>
</operation>

<operation id="31" st_id="2" stage="1" lat="1">
<core>NULL</core>
<MemPortIdVec></MemPortIdVec>
<condition id="-1">
<or_exp><and_exp></and_exp></or_exp>
</condition>

<Node id="27" bw="0" op_0_bw="0" op_1_bw="0">
<![CDATA[
for.inc100.split_ifconv:3 %specloopname_ln166 = specloopname void @_ssdm_op_SpecLoopName, void @empty_13

]]></Node>
<StgValue><ssdm name="specloopname_ln166"/></StgValue>
</operation>

<operation id="32" st_id="2" stage="1" lat="1">
<core>NULL</core>
<MemPortIdVec></MemPortIdVec>
<condition id="-1">
<or_exp><and_exp></and_exp></or_exp>
</condition>

<Node id="28" bw="9" op_0_bw="32" op_1_bw="64" op_2_bw="64">
<![CDATA[
for.inc100.split_ifconv:4 %state_re_addr = getelementptr i32 %state_re, i64 0, i64 %zext_ln166

]]></Node>
<StgValue><ssdm name="state_re_addr"/></StgValue>
</operation>

<operation id="33" st_id="2" stage="1" lat="1">
<core>NULL</core>
<MemPortIdVec></MemPortIdVec>
<condition id="-1">
<or_exp><and_exp></and_exp></or_exp>
</condition>

<Node id="29" bw="9" op_0_bw="32" op_1_bw="64" op_2_bw="64">
<![CDATA[
for.inc100.split_ifconv:5 %state_im_addr = getelementptr i32 %state_im, i64 0, i64 %zext_ln166

]]></Node>
<StgValue><ssdm name="state_im_addr"/></StgValue>
</operation>

<operation id="34" st_id="2" stage="1" lat="2">
<core>RAM_2P_BRAM</core>
<MemPortIdVec></MemPortIdVec>
<condition id="-1">
<or_exp><and_exp><literal name="state_cur_030126_read" val="1"/>
</and_exp></or_exp>
</condition>

<Node id="31" bw="32" op_0_bw="9">
<![CDATA[
for.inc100.split_ifconv:7 %bufB_re_load = load i9 %bufB_re_addr

]]></Node>
<StgValue><ssdm name="bufB_re_load"/></StgValue>
</operation>

<operation id="35" st_id="2" stage="1" lat="2">
<core>RAM_2P_BRAM</core>
<MemPortIdVec></MemPortIdVec>
<condition id="-1">
<or_exp><and_exp><literal name="state_cur_030126_read" val="1"/>
</and_exp></or_exp>
</condition>

<Node id="33" bw="32" op_0_bw="9">
<![CDATA[
for.inc100.split_ifconv:9 %bufB_im_load = load i9 %bufB_im_addr

]]></Node>
<StgValue><ssdm name="bufB_im_load"/></StgValue>
</operation>

<operation id="36" st_id="2" stage="1" lat="2">
<core>RAM_2P_BRAM</core>
<MemPortIdVec></MemPortIdVec>
<condition id="-1">
<or_exp><and_exp><literal name="state_cur_030126_read" val="0"/>
</and_exp></or_exp>
</condition>

<Node id="35" bw="32" op_0_bw="9">
<![CDATA[
for.inc100.split_ifconv:11 %bufA_re_load = load i9 %bufA_re_addr

]]></Node>
<StgValue><ssdm name="bufA_re_load"/></StgValue>
</operation>

<operation id="37" st_id="2" stage="1" lat="2">
<core>RAM_2P_BRAM</core>
<MemPortIdVec></MemPortIdVec>
<condition id="-1">
<or_exp><and_exp><literal name="state_cur_030126_read" val="0"/>
</and_exp></or_exp>
</condition>

<Node id="37" bw="32" op_0_bw="9">
<![CDATA[
for.inc100.split_ifconv:13 %bufA_im_load = load i9 %bufA_im_addr

]]></Node>
<StgValue><ssdm name="bufA_im_load"/></StgValue>
</operation>

<operation id="38" st_id="2" stage="1" lat="1">
<core>Sel</core>
<MemPortIdVec></MemPortIdVec>
<condition id="-1">
<or_exp><and_exp></and_exp></or_exp>
</condition>

<Node id="38" bw="32" op_0_bw="1" op_1_bw="32" op_2_bw="32">
<![CDATA[
for.inc100.split_ifconv:14 %empty = select i1 %state_cur_030126_read, i32 %bufB_re_load, i32 %bufA_re_load

]]></Node>
<StgValue><ssdm name="empty"/></StgValue>
</operation>

<operation id="39" st_id="2" stage="1" lat="1">
<core>Sel</core>
<MemPortIdVec></MemPortIdVec>
<condition id="-1">
<or_exp><and_exp></and_exp></or_exp>
</condition>

<Node id="39" bw="32" op_0_bw="1" op_1_bw="32" op_2_bw="32">
<![CDATA[
for.inc100.split_ifconv:15 %empty_57 = select i1 %state_cur_030126_read, i32 %bufB_im_load, i32 %bufA_im_load

]]></Node>
<StgValue><ssdm name="empty_57"/></StgValue>
</operation>

<operation id="40" st_id="2" stage="1" lat="1">
<core>RAM_2P_BRAM</core>
<MemPortIdVec></MemPortIdVec>
<condition id="-1">
<or_exp><and_exp></and_exp></or_exp>
</condition>

<Node id="40" bw="0" op_0_bw="32" op_1_bw="9">
<![CDATA[
for.inc100.split_ifconv:16 %store_ln166 = store i32 %empty, i9 %state_re_addr

]]></Node>
<StgValue><ssdm name="store_ln166"/></StgValue>
</operation>

<operation id="41" st_id="2" stage="1" lat="1">
<core>RAM_2P_BRAM</core>
<MemPortIdVec></MemPortIdVec>
<condition id="-1">
<or_exp><and_exp></and_exp></or_exp>
</condition>

<Node id="41" bw="0" op_0_bw="32" op_1_bw="9">
<![CDATA[
for.inc100.split_ifconv:17 %store_ln166 = store i32 %empty_57, i9 %state_im_addr

]]></Node>
<StgValue><ssdm name="store_ln166"/></StgValue>
</operation>

<operation id="42" st_id="2" stage="1" lat="1">
<core>NULL</core>
<MemPortIdVec></MemPortIdVec>
<condition id="-1">
<or_exp><and_exp></and_exp></or_exp>
</condition>

<Node id="43" bw="0" op_0_bw="0">
<![CDATA[
for.inc100.split_ifconv:19 %br_ln166 = br void %for.inc100

]]></Node>
<StgValue><ssdm name="br_ln166"/></StgValue>
</operation>
</state>
</state_list>


<ports>
</ports>


<dataflows>
</dataflows>


</stg>
